README.md
setup.cfg
setup.py
barbershop/__init__.py
barbershop/external_functions.py
barbershop.egg-info/PKG-INFO
barbershop.egg-info/SOURCES.txt
barbershop.egg-info/dependency_links.txt
barbershop.egg-info/not-zip-safe
barbershop.egg-info/requires.txt
barbershop.egg-info/top_level.txt