Metadata-Version: 1.0
Name: barbershop
Version: 1.0
Summary: A Python package that aids the user in making dynamic cuts to data in various parameter spaces, using a simple GUI.
Home-page: https://github.com/ojhall94/barbershop
Author: Oliver James Hall
Author-email: ojh251@student.bham.ac.uk
License: MIT
Platform: UNKNOWN
